pyspark_streaming_base/__init__.py
pyspark_streaming_base/app/__init__.py
pyspark_streaming_base/app/app.py
pyspark_streaming_base/app/streaming_app.py
pyspark_streaming_base/logging/__init__.py
pyspark_streaming_base/py.typed
pyspark_streaming_base/sinks/__init__.py
pyspark_streaming_base/sinks/delta_sink.py
pyspark_streaming_base/sinks/streaming_sink.py
pyspark_streaming_base/sources/__init__.py
pyspark_streaming_base/sources/delta_source.py
pyspark_streaming_base/sources/kafka_source.py
pyspark_streaming_base/sources/streaming_source.py
pyspark_streaming_base-0.1.2.dist-info/WHEEL
pyspark_streaming_base-0.1.2.dist-info/METADATA
pyspark_streaming_base-0.1.2.dist-info/RECORD
