Metadata-Version: 2.3
Name: pyspark-streaming-base
Version: 0.1.2
Summary: This project provides a set of base classes that simplify the art of crafting bullet-proof Spark Structured Streaming applications.
Keywords: pyspark,structured streaming,kafka,delta lake
Author: Scott Haines
Author-email: Scott Haines <newfrontcreative@gmail.com>
Requires-Dist: delta-spark>=4.0.0
Requires-Dist: pyspark>=4.0.1
Requires-Dist: python-dotenv>=1.2.1
Requires-Dist: ruff>=0.14.4
Requires-Dist: uv-build>=0.9.8,<0.10.0
Requires-Python: >=3.13
Project-URL: PyPI, https://pypi.org/project/pyspark-streaming-base/
Project-URL: Releases, https://github.com/datacircus/pyspark-streaming-base/releases
Project-URL: Repository, https://github.com/datacircus/pyspark-streaming-base
